ovn_octavia_provider/__init__.py
ovn_octavia_provider/agent.py
ovn_octavia_provider/driver.py
ovn_octavia_provider/event.py
ovn_octavia_provider/helper.py
ovn_octavia_provider/i18n.py
ovn_octavia_provider/maintenance.py
ovn_octavia_provider/cmd/__init__.py
ovn_octavia_provider/cmd/octavia_ovn_db_sync_util.py
ovn_octavia_provider/common/clients.py
ovn_octavia_provider/common/config.py
ovn_octavia_provider/common/constants.py
ovn_octavia_provider/common/exceptions.py
ovn_octavia_provider/common/utils.py
ovn_octavia_provider/hacking/__init__.py
ovn_octavia_provider/hacking/checks.py
ovn_octavia_provider/ovsdb/impl_idl_ovn.py
ovn_octavia_provider/ovsdb/ovsdb_monitor.py
ovn_octavia_provider/tests/__init__.py
ovn_octavia_provider/tests/functional/__init__.py
ovn_octavia_provider/tests/functional/base.py
ovn_octavia_provider/tests/functional/requirements.txt
ovn_octavia_provider/tests/functional/test_agent.py
ovn_octavia_provider/tests/functional/test_driver.py
ovn_octavia_provider/tests/functional/test_integration.py
ovn_octavia_provider/tests/unit/__init__.py
ovn_octavia_provider/tests/unit/base.py
ovn_octavia_provider/tests/unit/fakes.py
ovn_octavia_provider/tests/unit/test_agent.py
ovn_octavia_provider/tests/unit/test_cmd.py
ovn_octavia_provider/tests/unit/test_driver.py
ovn_octavia_provider/tests/unit/test_hacking.py
ovn_octavia_provider/tests/unit/test_helper.py
ovn_octavia_provider/tests/unit/test_maintenance.py
ovn_octavia_provider/tests/unit/common/__init__.py
ovn_octavia_provider/tests/unit/common/test_clients.py
ovn_octavia_provider/tests/unit/common/test_utils.py
ovn_octavia_provider/tests/unit/hacking/__init__.py
ovn_octavia_provider/tests/unit/hacking/test_checks.py
ovn_octavia_provider/tests/unit/ovsdb/__init__.py
ovn_octavia_provider/tests/unit/ovsdb/test_impl_idl_ovn.py
ovn_octavia_provider/tests/unit/ovsdb/test_ovsdb_monitor.py
ovn_octavia_provider/tests/unit/schemas/ovn-nb.ovsschema
ovn_octavia_provider/tests/unit/schemas/ovn-sb.ovsschema
ovn_octavia_provider-9.0.0.dist-info/AUTHORS
ovn_octavia_provider-9.0.0.dist-info/LICENSE
ovn_octavia_provider-9.0.0.dist-info/METADATA
ovn_octavia_provider-9.0.0.dist-info/WHEEL
ovn_octavia_provider-9.0.0.dist-info/entry_points.txt
ovn_octavia_provider-9.0.0.dist-info/pbr.json
ovn_octavia_provider-9.0.0.dist-info/top_level.txt
ovn_octavia_provider-9.0.0.dist-info/RECORD
