Metadata-Version: 2.1
Name: ovn-octavia-provider
Version: 9.0.0
Summary: OpenStack Octavia integration with OVN
Home-page: https://docs.openstack.org/ovn-octavia-provider/latest/
Author: OpenStack
Author-email: openstack-discuss@lists.openstack.org
Classifier: Environment :: OpenStack
Classifier: Intended Audience :: Information Technology
Classifier: Intended Audience :: System Administrators
Classifier: License :: OSI Approved :: Apache Software License
Classifier: Operating System :: POSIX :: Linux
Classifier: Programming Language :: Python
Classifier: Programming Language :: Python :: 3
Classifier: Programming Language :: Python :: 3.10
Classifier: Programming Language :: Python :: 3.11
Classifier: Programming Language :: Python :: 3.12
Requires-Python: >=3.10
License-File: LICENSE
License-File: AUTHORS
Requires-Dist: keystoneauth1 >=3.14.0
Requires-Dist: netaddr >=0.7.18
Requires-Dist: neutron-lib >=3.8.0
Requires-Dist: openstacksdk >=0.103.0
Requires-Dist: oslo.config >=8.0.0
Requires-Dist: oslo.log >=4.3.0
Requires-Dist: oslo.messaging >=12.4.0
Requires-Dist: oslo.serialization >=2.28.1
Requires-Dist: oslo.utils >=4.5.0
Requires-Dist: ovs >=2.10.0
Requires-Dist: ovsdbapp >=2.1.0
Requires-Dist: pbr >=4.0.0
Requires-Dist: SQLAlchemy >=1.4.23
Requires-Dist: tenacity >=6.0.0
Requires-Dist: octavia-lib >=2.2.0
